magicparams/__init__.py
magicparams/magic_params_class.py
magicparams-0.1.0.dist-info/METADATA
magicparams-0.1.0.dist-info/WHEEL
magicparams-0.1.0.dist-info/top_level.txt
magicparams-0.1.0.dist-info/RECORD
