Metadata-Version: 2.1
Name: magicparams
Version: 0.1.0
Summary: Seamless and easy to use parameters manager for Machine Learning pipelines
Home-page: https://github.com/shudima/magicparams
License: UNKNOWN
Keywords: Machine Learning
Platform: UNKNOWN
